gen_adequacy/__init__.py
gen_adequacy/generator.py
gen_adequacy/ieee_rts.py
gen_adequacy/randomvar.py
gen_adequacy/system.py
gen_adequacy/util.py
gen_adequacy-0.5.0.dist-info/LICENSE
gen_adequacy-0.5.0.dist-info/METADATA
gen_adequacy-0.5.0.dist-info/WHEEL
gen_adequacy-0.5.0.dist-info/top_level.txt
gen_adequacy-0.5.0.dist-info/RECORD
