Metadata-Version: 2.1
Name: gen-adequacy
Version: 0.5.0
Summary: Tools for single node generation adequacy analysis
Home-page: https://github.com/simontindemans/gen_adequacy
Author: Simon Tindemans
Author-email: s.h.tindemans@tudelft.nl
License: UNKNOWN
Platform: UNKNOWN
Classifier: Development Status :: 4 - Beta
Classifier: Intended Audience :: Science/Research
Classifier: License :: OSI Approved :: Mozilla Public License 2.0 (MPL 2.0)
Classifier: Natural Language :: English
Classifier: Programming Language :: Python :: 3
Classifier: Topic :: Scientific/Engineering
Requires-Python: >=3.5
License-File: LICENSE
Requires-Dist: numpy
